application_example/__init__.py
application_example/example.py
kc_test_leo_silva-0.0.3.dist-info/METADATA
kc_test_leo_silva-0.0.3.dist-info/WHEEL
kc_test_leo_silva-0.0.3.dist-info/top_level.txt
kc_test_leo_silva-0.0.3.dist-info/RECORD
